{
    "/js/app.js": "/js/app.js",
    "/css/app.css": "/css/app.css",
    "/css/plantilla.css": "/css/plantilla.css",
    "/css/portal.css": "/css/portal.css",
    "/js/jquery.js": "/js/jquery.js",
    "/js/plantilla.js": "/js/plantilla.js",
    "/js/portal.js": "/js/portal.js",
    "/js/portal_custom.js": "/js/portal_custom.js",
    "/imgs/1682712649_logo.jpg": "/imgs/1682712649_logo.jpg",
    "/imgs/1714488027_mision_img.jpg": "/imgs/1714488027_mision_img.jpg",
    "/imgs/1714488027_nosotros_img.jpg": "/imgs/1714488027_nosotros_img.jpg",
    "/imgs/1714488027_vision_img.jpg": "/imgs/1714488027_vision_img.jpg",
    "/imgs/1714488423_servicios_img.jpg": "/imgs/1714488423_servicios_img.jpg",
    "/imgs/avatar.png": "/imgs/avatar.png",
    "/imgs/comprobantes/1714246060_1.pdf": "/imgs/comprobantes/1714246060_1.pdf",
    "/imgs/comprobantes/1714494532_2.pdf": "/imgs/comprobantes/1714494532_2.pdf",
    "/imgs/configuracion_pagos/1714158455_1.png": "/imgs/configuracion_pagos/1714158455_1.png",
    "/imgs/configuracion_pagos/1714158657_1.png": "/imgs/configuracion_pagos/1714158657_1.png",
    "/imgs/configuracion_pagos/1714158673_1.png": "/imgs/configuracion_pagos/1714158673_1.png",
    "/imgs/configuracion_pagos/1714158676_1.png": "/imgs/configuracion_pagos/1714158676_1.png",
    "/imgs/configuracion_pagos/1714158710_1.png": "/imgs/configuracion_pagos/1714158710_1.png",
    "/imgs/configuracion_pagos/1714158714_1.png": "/imgs/configuracion_pagos/1714158714_1.png",
    "/imgs/configuracion_pagos/1714158718_1.png": "/imgs/configuracion_pagos/1714158718_1.png",
    "/imgs/configuracion_pagos/1714158732_2.png": "/imgs/configuracion_pagos/1714158732_2.png",
    "/imgs/configuracion_pagos/1714158736_2.png": "/imgs/configuracion_pagos/1714158736_2.png",
    "/imgs/configuracion_pagos/1714484423_1.png": "/imgs/configuracion_pagos/1714484423_1.png",
    "/imgs/fondo_seccion.webp": "/imgs/fondo_seccion.webp",
    "/imgs/fondo_seccion2.jpg": "/imgs/fondo_seccion2.jpg",
    "/imgs/fondo_seccion3.jpg": "/imgs/fondo_seccion3.jpg",
    "/imgs/login.jpg": "/imgs/login.jpg",
    "/imgs/login.webp": "/imgs/login.webp",
    "/imgs/login2.webp": "/imgs/login2.webp",
    "/imgs/login3.webp": "/imgs/login3.webp",
    "/imgs/logo.webp": "/imgs/logo.webp",
    "/imgs/productos/1682372735_4.jpg": "/imgs/productos/1682372735_4.jpg",
    "/imgs/productos/1682372808_5.jpg": "/imgs/productos/1682372808_5.jpg",
    "/imgs/productos/1682372843_6.jpg": "/imgs/productos/1682372843_6.jpg",
    "/imgs/productos/1682372848_6.jpg": "/imgs/productos/1682372848_6.jpg",
    "/imgs/productos/1682372874_7.jpg": "/imgs/productos/1682372874_7.jpg",
    "/imgs/productos/1682372879_7.jpg": "/imgs/productos/1682372879_7.jpg",
    "/imgs/productos/1682696491_7.jpg": "/imgs/productos/1682696491_7.jpg",
    "/imgs/productos/1682696493_7.jpg": "/imgs/productos/1682696493_7.jpg",
    "/imgs/productos/1682696496_7.jpg": "/imgs/productos/1682696496_7.jpg",
    "/imgs/productos/default.png": "/imgs/productos/default.png",
    "/imgs/users/1666903970_JPERES.jpg": "/imgs/users/1666903970_JPERES.jpg",
    "/imgs/users/1674665167_MGONZALES.jpg": "/imgs/users/1674665167_MGONZALES.jpg",
    "/imgs/users/default.png": "/imgs/users/default.png",
    "/images/about-01.jpg": "/images/about-01.jpg",
    "/images/about-02.jpg": "/images/about-02.jpg",
    "/images/avatar-01.jpg": "/images/avatar-01.jpg",
    "/images/banner-01.jpg": "/images/banner-01.jpg",
    "/images/banner-02.jpg": "/images/banner-02.jpg",
    "/images/banner-03.jpg": "/images/banner-03.jpg",
    "/images/banner-04.jpg": "/images/banner-04.jpg",
    "/images/banner-05.jpg": "/images/banner-05.jpg",
    "/images/banner-06.jpg": "/images/banner-06.jpg",
    "/images/banner-07.jpg": "/images/banner-07.jpg",
    "/images/banner-08.jpg": "/images/banner-08.jpg",
    "/images/banner-09.jpg": "/images/banner-09.jpg",
    "/images/bg-01.jpg": "/images/bg-01.jpg",
    "/images/bg-02.jpg": "/images/bg-02.jpg",
    "/images/blog-01.jpg": "/images/blog-01.jpg",
    "/images/blog-02.jpg": "/images/blog-02.jpg",
    "/images/blog-03.jpg": "/images/blog-03.jpg",
    "/images/blog-04.jpg": "/images/blog-04.jpg",
    "/images/blog-05.jpg": "/images/blog-05.jpg",
    "/images/blog-06.jpg": "/images/blog-06.jpg",
    "/images/gallery-01.jpg": "/images/gallery-01.jpg",
    "/images/gallery-02.jpg": "/images/gallery-02.jpg",
    "/images/gallery-03.jpg": "/images/gallery-03.jpg",
    "/images/gallery-04.jpg": "/images/gallery-04.jpg",
    "/images/gallery-05.jpg": "/images/gallery-05.jpg",
    "/images/gallery-06.jpg": "/images/gallery-06.jpg",
    "/images/gallery-07.jpg": "/images/gallery-07.jpg",
    "/images/gallery-08.jpg": "/images/gallery-08.jpg",
    "/images/gallery-09.jpg": "/images/gallery-09.jpg",
    "/images/icons/favicon.png": "/images/icons/favicon.png",
    "/images/icons/icon-close.png": "/images/icons/icon-close.png",
    "/images/icons/icon-close2.png": "/images/icons/icon-close2.png",
    "/images/icons/icon-email.png": "/images/icons/icon-email.png",
    "/images/icons/icon-heart-01.png": "/images/icons/icon-heart-01.png",
    "/images/icons/icon-heart-02.png": "/images/icons/icon-heart-02.png",
    "/images/icons/icon-next.png": "/images/icons/icon-next.png",
    "/images/icons/icon-pay-01.png": "/images/icons/icon-pay-01.png",
    "/images/icons/icon-pay-02.png": "/images/icons/icon-pay-02.png",
    "/images/icons/icon-pay-03.png": "/images/icons/icon-pay-03.png",
    "/images/icons/icon-pay-04.png": "/images/icons/icon-pay-04.png",
    "/images/icons/icon-pay-05.png": "/images/icons/icon-pay-05.png",
    "/images/icons/icon-prev.png": "/images/icons/icon-prev.png",
    "/images/icons/logo-01.png": "/images/icons/logo-01.png",
    "/images/icons/logo-02.png": "/images/icons/logo-02.png",
    "/images/icons/pin.png": "/images/icons/pin.png",
    "/images/item-cart-01.jpg": "/images/item-cart-01.jpg",
    "/images/item-cart-02.jpg": "/images/item-cart-02.jpg",
    "/images/item-cart-03.jpg": "/images/item-cart-03.jpg",
    "/images/item-cart-04.jpg": "/images/item-cart-04.jpg",
    "/images/item-cart-05.jpg": "/images/item-cart-05.jpg",
    "/images/product-01.jpg": "/images/product-01.jpg",
    "/images/product-02.jpg": "/images/product-02.jpg",
    "/images/product-03.jpg": "/images/product-03.jpg",
    "/images/product-04.jpg": "/images/product-04.jpg",
    "/images/product-05.jpg": "/images/product-05.jpg",
    "/images/product-06.jpg": "/images/product-06.jpg",
    "/images/product-07.jpg": "/images/product-07.jpg",
    "/images/product-08.jpg": "/images/product-08.jpg",
    "/images/product-09.jpg": "/images/product-09.jpg",
    "/images/product-10.jpg": "/images/product-10.jpg",
    "/images/product-11.jpg": "/images/product-11.jpg",
    "/images/product-12.jpg": "/images/product-12.jpg",
    "/images/product-13.jpg": "/images/product-13.jpg",
    "/images/product-14.jpg": "/images/product-14.jpg",
    "/images/product-15.jpg": "/images/product-15.jpg",
    "/images/product-16.jpg": "/images/product-16.jpg",
    "/images/product-detail-01.jpg": "/images/product-detail-01.jpg",
    "/images/product-detail-02.jpg": "/images/product-detail-02.jpg",
    "/images/product-detail-03.jpg": "/images/product-detail-03.jpg",
    "/images/product-min-01.jpg": "/images/product-min-01.jpg",
    "/images/product-min-02.jpg": "/images/product-min-02.jpg",
    "/images/product-min-03.jpg": "/images/product-min-03.jpg",
    "/images/slide-01.jpg": "/images/slide-01.jpg",
    "/images/slide-02.jpg": "/images/slide-02.jpg",
    "/images/slide-03.jpg": "/images/slide-03.jpg",
    "/images/slide-04.jpg": "/images/slide-04.jpg",
    "/images/slide-05.jpg": "/images/slide-05.jpg",
    "/images/slide-06.jpg": "/images/slide-06.jpg",
    "/images/slide-07.jpg": "/images/slide-07.jpg",
    "/images/thumb-01.jpg": "/images/thumb-01.jpg",
    "/images/thumb-02.jpg": "/images/thumb-02.jpg",
    "/images/thumb-03.jpg": "/images/thumb-03.jpg",
    "/webfonts/fa-brands-400.eot": "/webfonts/fa-brands-400.eot",
    "/webfonts/fa-brands-400.svg": "/webfonts/fa-brands-400.svg",
    "/webfonts/fa-brands-400.ttf": "/webfonts/fa-brands-400.ttf",
    "/webfonts/fa-brands-400.woff": "/webfonts/fa-brands-400.woff",
    "/webfonts/fa-brands-400.woff2": "/webfonts/fa-brands-400.woff2",
    "/webfonts/fa-regular-400.eot": "/webfonts/fa-regular-400.eot",
    "/webfonts/fa-regular-400.svg": "/webfonts/fa-regular-400.svg",
    "/webfonts/fa-regular-400.ttf": "/webfonts/fa-regular-400.ttf",
    "/webfonts/fa-regular-400.woff": "/webfonts/fa-regular-400.woff",
    "/webfonts/fa-regular-400.woff2": "/webfonts/fa-regular-400.woff2",
    "/webfonts/fa-solid-900.eot": "/webfonts/fa-solid-900.eot",
    "/webfonts/fa-solid-900.svg": "/webfonts/fa-solid-900.svg",
    "/webfonts/fa-solid-900.ttf": "/webfonts/fa-solid-900.ttf",
    "/webfonts/fa-solid-900.woff": "/webfonts/fa-solid-900.woff",
    "/webfonts/fa-solid-900.woff2": "/webfonts/fa-solid-900.woff2",
    "/webfont/Linearicons-Free.eot": "/webfont/Linearicons-Free.eot",
    "/webfont/Linearicons-Free.svg": "/webfont/Linearicons-Free.svg",
    "/webfont/Linearicons-Free.ttf": "/webfont/Linearicons-Free.ttf",
    "/webfont/Linearicons-Free.woff": "/webfont/Linearicons-Free.woff",
    "/webfont/Linearicons-Free.woff2": "/webfont/Linearicons-Free.woff2",
    "/fonts/Material-Design-Iconic-Font.eot": "/fonts/Material-Design-Iconic-Font.eot",
    "/fonts/Material-Design-Iconic-Font.svg": "/fonts/Material-Design-Iconic-Font.svg",
    "/fonts/Material-Design-Iconic-Font.ttf": "/fonts/Material-Design-Iconic-Font.ttf",
    "/fonts/Material-Design-Iconic-Font.woff": "/fonts/Material-Design-Iconic-Font.woff",
    "/fonts/Material-Design-Iconic-Font.woff2": "/fonts/Material-Design-Iconic-Font.woff2",
    "/fonts/Montserrat/Montserrat-Black.ttf": "/fonts/Montserrat/Montserrat-Black.ttf",
    "/fonts/Montserrat/Montserrat-BlackItalic.ttf": "/fonts/Montserrat/Montserrat-BlackItalic.ttf",
    "/fonts/Montserrat/Montserrat-Bold.ttf": "/fonts/Montserrat/Montserrat-Bold.ttf",
    "/fonts/Montserrat/Montserrat-BoldItalic.ttf": "/fonts/Montserrat/Montserrat-BoldItalic.ttf",
    "/fonts/Montserrat/Montserrat-ExtraBold.ttf": "/fonts/Montserrat/Montserrat-ExtraBold.ttf",
    "/fonts/Montserrat/Montserrat-ExtraBoldItalic.ttf": "/fonts/Montserrat/Montserrat-ExtraBoldItalic.ttf",
    "/fonts/Montserrat/Montserrat-ExtraLight.ttf": "/fonts/Montserrat/Montserrat-ExtraLight.ttf",
    "/fonts/Montserrat/Montserrat-ExtraLightItalic.ttf": "/fonts/Montserrat/Montserrat-ExtraLightItalic.ttf",
    "/fonts/Montserrat/Montserrat-Italic.ttf": "/fonts/Montserrat/Montserrat-Italic.ttf",
    "/fonts/Montserrat/Montserrat-Light.ttf": "/fonts/Montserrat/Montserrat-Light.ttf",
    "/fonts/Montserrat/Montserrat-LightItalic.ttf": "/fonts/Montserrat/Montserrat-LightItalic.ttf",
    "/fonts/Montserrat/Montserrat-Medium.ttf": "/fonts/Montserrat/Montserrat-Medium.ttf",
    "/fonts/Montserrat/Montserrat-MediumItalic.ttf": "/fonts/Montserrat/Montserrat-MediumItalic.ttf",
    "/fonts/Montserrat/Montserrat-Regular.ttf": "/fonts/Montserrat/Montserrat-Regular.ttf",
    "/fonts/Montserrat/Montserrat-SemiBold.ttf": "/fonts/Montserrat/Montserrat-SemiBold.ttf",
    "/fonts/Montserrat/Montserrat-SemiBoldItalic.ttf": "/fonts/Montserrat/Montserrat-SemiBoldItalic.ttf",
    "/fonts/Montserrat/Montserrat-Thin.ttf": "/fonts/Montserrat/Montserrat-Thin.ttf",
    "/fonts/Montserrat/Montserrat-ThinItalic.ttf": "/fonts/Montserrat/Montserrat-ThinItalic.ttf",
    "/fonts/Montserrat/OFL.txt": "/fonts/Montserrat/OFL.txt",
    "/fonts/PlayfairDisplay/OFL.txt": "/fonts/PlayfairDisplay/OFL.txt",
    "/fonts/PlayfairDisplay/PlayfairDisplay-Black.ttf": "/fonts/PlayfairDisplay/PlayfairDisplay-Black.ttf",
    "/fonts/PlayfairDisplay/PlayfairDisplay-BlackItalic.ttf": "/fonts/PlayfairDisplay/PlayfairDisplay-BlackItalic.ttf",
    "/fonts/PlayfairDisplay/PlayfairDisplay-Bold.ttf": "/fonts/PlayfairDisplay/PlayfairDisplay-Bold.ttf",
    "/fonts/PlayfairDisplay/PlayfairDisplay-BoldItalic.ttf": "/fonts/PlayfairDisplay/PlayfairDisplay-BoldItalic.ttf",
    "/fonts/PlayfairDisplay/PlayfairDisplay-Italic.ttf": "/fonts/PlayfairDisplay/PlayfairDisplay-Italic.ttf",
    "/fonts/PlayfairDisplay/PlayfairDisplay-Regular.ttf": "/fonts/PlayfairDisplay/PlayfairDisplay-Regular.ttf",
    "/fonts/Poppins/Poppins-Black.ttf": "/fonts/Poppins/Poppins-Black.ttf",
    "/fonts/Poppins/Poppins-BlackItalic.ttf": "/fonts/Poppins/Poppins-BlackItalic.ttf",
    "/fonts/Poppins/Poppins-Bold.ttf": "/fonts/Poppins/Poppins-Bold.ttf",
    "/fonts/Poppins/Poppins-BoldItalic.ttf": "/fonts/Poppins/Poppins-BoldItalic.ttf",
    "/fonts/Poppins/Poppins-ExtraBold.ttf": "/fonts/Poppins/Poppins-ExtraBold.ttf",
    "/fonts/Poppins/Poppins-ExtraBoldItalic.ttf": "/fonts/Poppins/Poppins-ExtraBoldItalic.ttf",
    "/fonts/Poppins/Poppins-ExtraLight.ttf": "/fonts/Poppins/Poppins-ExtraLight.ttf",
    "/fonts/Poppins/Poppins-ExtraLightItalic.ttf": "/fonts/Poppins/Poppins-ExtraLightItalic.ttf",
    "/fonts/Poppins/Poppins-Italic.ttf": "/fonts/Poppins/Poppins-Italic.ttf",
    "/fonts/Poppins/Poppins-Light.ttf": "/fonts/Poppins/Poppins-Light.ttf",
    "/fonts/Poppins/Poppins-LightItalic.ttf": "/fonts/Poppins/Poppins-LightItalic.ttf",
    "/fonts/Poppins/Poppins-Medium.ttf": "/fonts/Poppins/Poppins-Medium.ttf",
    "/fonts/Poppins/Poppins-MediumItalic.ttf": "/fonts/Poppins/Poppins-MediumItalic.ttf",
    "/fonts/Poppins/Poppins-Regular.ttf": "/fonts/Poppins/Poppins-Regular.ttf",
    "/fonts/Poppins/Poppins-SemiBold.ttf": "/fonts/Poppins/Poppins-SemiBold.ttf",
    "/fonts/Poppins/Poppins-SemiBoldItalic.ttf": "/fonts/Poppins/Poppins-SemiBoldItalic.ttf",
    "/fonts/Poppins/Poppins-Thin.ttf": "/fonts/Poppins/Poppins-Thin.ttf",
    "/fonts/Poppins/Poppins-ThinItalic.ttf": "/fonts/Poppins/Poppins-ThinItalic.ttf",
    "/fonts/vendor/element-ui/lib/theme-chalk/element-icons.ttf": "/fonts/vendor/element-ui/lib/theme-chalk/element-icons.ttf",
    "/fonts/vendor/element-ui/lib/theme-chalk/element-icons.woff": "/fonts/vendor/element-ui/lib/theme-chalk/element-icons.woff"
}
